Metadata-Version: 2.1
Name: TornikeTsikarishvili
Version: 0.0.1
Summary: simple Calculator
Home-page: 
Author: Tornike Tsikarishvili
Author-email: tornike.tsikarishvili.1@btu.edu.ge
License: MIT
Keywords: calculator
Classifier: Development Status :: 5 - Production/Stable
Classifier: Intended Audience :: Education
Classifier: Operating System :: Microsoft :: Windows :: Windows 11
Classifier: License :: OSI Approved :: MIT License
Classifier: Programming Language :: Python :: 3
License-File: LICENSE.txt
